topsis/__init__.py
topsis/topsis.py
topsis_101703396-0.0.1.dist-info/LICENSE.txt
topsis_101703396-0.0.1.dist-info/METADATA
topsis_101703396-0.0.1.dist-info/WHEEL
topsis_101703396-0.0.1.dist-info/top_level.txt
topsis_101703396-0.0.1.dist-info/RECORD
